streamlit_data_management/__init__.py
streamlit_data_management/dashboard.py
streamlit_data_management-0.1.1.dist-info/WHEEL
streamlit_data_management-0.1.1.dist-info/METADATA
streamlit_data_management-0.1.1.dist-info/RECORD
