Metadata-Version: 2.1
Name: streamlit-data-management
Version: 0.1.1
Summary: 
Author: Denver Noell
Author-email: dnoell@ppeng.com
Requires-Python: >=3.10,<4.0
Classifier: Programming Language :: Python :: 3
Classifier: Programming Language :: Python :: 3.10
Requires-Dist: arrow (>=1.2.3,<2.0.0)
Requires-Dist: pandas (>=1.5.2,<2.0.0)
Requires-Dist: plotly (>=5.12.0,<6.0.0)
Requires-Dist: supabase (>=0.7.1,<0.8.0)
